udger/__init__.py
udger/base.py
udger/downloader.py
udger/parser.py
udger/queries.py
udger/wdetector.py
udger-4.0.2.dist-info/LICENSE
udger-4.0.2.dist-info/METADATA
udger-4.0.2.dist-info/WHEEL
udger-4.0.2.dist-info/top_level.txt
udger-4.0.2.dist-info/zip-safe
udger-4.0.2.dist-info/RECORD
