Metadata-Version: 2.1
Name: udger
Version: 4.0.2
Summary: Fast and reliable User Agent parser and IP classifier for Python
Home-page: https://github.com/udger/udger-python
Author: The Udger Team
Author-email: info@udger.com
License: BSD
Platform: any
Classifier: Development Status :: 5 - Production/Stable
Classifier: Intended Audience :: Developers
Classifier: License :: OSI Approved :: BSD License
Classifier: Operating System :: OS Independent
Classifier: Programming Language :: Python
Classifier: Programming Language :: Python :: 2
Classifier: Programming Language :: Python :: 3
Classifier: Topic :: Software Development :: Libraries
License-File: LICENSE
